overfitting/__init__.py
overfitting/broker.py
overfitting/data.py
overfitting/order.py
overfitting/position.py
overfitting/strategy.py
overfitting/execution/__init__.py
overfitting/execution/slippage.py
overfitting/plot/__init__.py
overfitting/plot/graph.py
overfitting/plot/performance.py
overfitting/utils/__init__.py
overfitting/utils/entities.py
overfitting/utils/error.py
overfitting-0.1.9.dist-info/licenses/LICENSE
overfitting-0.1.9.dist-info/METADATA
overfitting-0.1.9.dist-info/WHEEL
overfitting-0.1.9.dist-info/top_level.txt
overfitting-0.1.9.dist-info/RECORD
