Metadata-Version: 2.4
Name: overfitting
Version: 0.1.9
Summary: A Robust Futures CryptoCurrency Backtesting Library.
Author-email: Dohyun Kim <dohyun.k.july@gmail.com>
License: MIT
Project-URL: Homepage, https://github.com/dohyunkjuly/overfitting
Project-URL: Source, https://github.com/dohyunkjuly/overfitting
Project-URL: Author, https://github.com/dohyunkjuly
Keywords: algo,bitcoin,ethereum,crypto,cryptocurrency,crypto derivatives,futures,finance,quantitative,liquidation,solana,systematic,quant,trading
Classifier: Intended Audience :: Developers
Classifier: License :: OSI Approved :: MIT License
Classifier: Framework :: Jupyter
Classifier: Programming Language :: Python
Classifier: Programming Language :: Python :: 3
Classifier: Operating System :: OS Independent
Classifier: Topic :: Office/Business :: Financial :: Investment
Requires-Python: >=3.8
License-File: LICENSE
Requires-Dist: numpy>=1.17.0
Requires-Dist: pandas>=0.25.0
Requires-Dist: seaborn
Requires-Dist: matplotlib
Requires-Dist: scipy
Provides-Extra: examples
Requires-Dist: notebook; extra == "examples"
Requires-Dist: ipykernel; extra == "examples"
Requires-Dist: ipython; extra == "examples"
Provides-Extra: dev
Requires-Dist: twine>=4.0.2; extra == "dev"
Dynamic: license-file
